MANIFEST.in
README.rst
buildout.cfg
requirements.txt
setup.py
version.txt
bob/__init__.py
bob.ip.annotator.egg-info/PKG-INFO
bob.ip.annotator.egg-info/SOURCES.txt
bob.ip.annotator.egg-info/dependency_links.txt
bob.ip.annotator.egg-info/entry_points.txt
bob.ip.annotator.egg-info/not-zip-safe
bob.ip.annotator.egg-info/requires.txt
bob.ip.annotator.egg-info/top_level.txt
bob/ip/__init__.py
bob/ip/annotator/__init__.py
bob/ip/annotator/gui.py
bob/ip/annotator/io.py
bob/ip/annotator/widgets.py
bob/ip/annotator/data/lenna.png
bob/ip/annotator/script/__init__.py
bob/ip/annotator/script/annotate.py
doc/api.rst
doc/guide.rst
doc/index.rst
doc/links.rst
doc/nitpick-exceptions.txt
doc/tkinter.inv
doc/tkinter.txt
doc/img/ROI.png
doc/img/VEINS.png
doc/img/alignment_annotation_1.png
doc/img/alignment_annotation_4.png
doc/img/annotate-main.png
doc/img/annotate-objects.png
doc/img/favicon.ico
doc/img/logo.png