Metadata-Version: 1.1
Name: bob.ip.annotator
Version: 1.0.1
Summary: A TkInter-based keypoint annotation tool for images
Home-page: https://gitlab.idiap.ch/bob/bob.ip.annotator
Author: Andre Anjos
Author-email: andre.anjos@idiap.ch
License: GPLv3
Platform: UNKNOWN
Classifier: Framework :: Bob
Classifier: Development Status :: 4 - Beta
Classifier: Intended Audience :: Developers
Classifier: License :: OSI Approved :: GNU General Public License v3 (GPLv3)
Classifier: Natural Language :: English
Classifier: Programming Language :: Python
Classifier: Programming Language :: Python :: 3
Classifier: Topic :: Software Development :: Libraries :: Python Modules
